{
  "name" : "User",
  "comment" : null,
  "fullColumn" : [ {
    "name" : "id",
    "comment" : null,
    "type" : null,
    "shortType" : null,
    "custom" : false,
    "ext" : { }
  }, {
    "name" : "uName",
    "comment" : null,
    "type" : "java.lang.String",
    "shortType" : null,
    "custom" : false,
    "ext" : { }
  }, {
    "name" : "uPassword",
    "comment" : null,
    "type" : "java.lang.String",
    "shortType" : null,
    "custom" : false,
    "ext" : { }
  }, {
    "name" : "roleId",
    "comment" : null,
    "type" : null,
    "shortType" : null,
    "custom" : false,
    "ext" : { }
  }, {
    "name" : "uQq",
    "comment" : null,
    "type" : "java.lang.String",
    "shortType" : null,
    "custom" : false,
    "ext" : { }
  }, {
    "name" : "uEmail",
    "comment" : null,
    "type" : "java.lang.String",
    "shortType" : null,
    "custom" : false,
    "ext" : { }
  }, {
    "name" : "uPhone",
    "comment" : null,
    "type" : "java.lang.String",
    "shortType" : null,
    "custom" : false,
    "ext" : { }
  }, {
    "name" : "uRegister",
    "comment" : null,
    "type" : "java.sql.Date",
    "shortType" : null,
    "custom" : false,
    "ext" : { }
  } ],
  "pkColumn" : null,
  "otherColumn" : null,
  "savePackageName" : "com.cn",
  "savePath" : "./src/main/resources",
  "saveModelName" : "MyApi"
}